[
  {
    "publishingOffice": "彦根地方気象台",
    "reportDatetime": "2026-04-23T05:00:00+09:00",
    "timeSeries": [
      {
        "timeDefines": [
          "2026-04-23T05:00:00+09:00",
          "2026-04-24T00:00:00+09:00"
        ],
        "areas": [
          {
            "area": {
              "name": "南部",
              "code": "250010"
            },
            "weatherCodes": [
              "302",
              "211"
            ],
            "weathers": [
              "雨　朝晩　くもり",
              "くもり　昼前　から　晴れ"
            ],
            "winds": [
              "南東の風　後　北西の風　やや強く",
              "北西の風　やや強く"
            ]
          },
          {
            "area": {
              "name": "北部",
              "code": "250020"
            },
            "weatherCodes": [
              "302",
              "211"
            ],
            "weathers": [
              "雨　朝晩　くもり",
              "くもり　昼前　から　晴れ"
            ],
            "winds": [
              "南東の風　後　北西の風　やや強く",
              "北西の風　やや強く"
            ]
          }
        ]
      },
      {
        "timeDefines": [
          "2026-04-23T06:00:00+09:00",
          "2026-04-23T12:00:00+09:00",
          "2026-04-23T18:00:00+09:00",
          "2026-04-24T00:00:00+09:00",
          "2026-04-24T06:00:00+09:00",
          "2026-04-24T12:00:00+09:00",
          "2026-04-24T18:00:00+09:00"
        ],
        "areas": [
          {
            "area": {
              "name": "南部",
              "code": "250010"
            },
            "pops": [
              "80",
              "90",
              "80",
              "10",
              "0",
              "0",
              "0"
            ]
          },
          {
            "area": {
              "name": "北部",
              "code": "250020"
            },
            "pops": [
              "70",
              "90",
              "70",
              "10",
              "0",
              "0",
              "0"
            ]
          }
        ]
      },
      {
        "timeDefines": [
          "2026-04-23T09:00:00+09:00",
          "2026-04-23T00:00:00+09:00",
          "2026-04-24T00:00:00+09:00",
          "2026-04-24T09:00:00+09:00"
        ],
        "areas": [
          {
            "area": {
              "name": "大津",
              "code": "60216"
            },
            "temps": [
              "14",
              "15",
              "12",
              "22"
            ]
          },
          {
            "area": {
              "name": "彦根",
              "code": "60131"
            },
            "temps": [
              "15",
              "15",
              "11",
              "19"
            ]
          }
        ]
      }
    ]
  },
  {
    "publishingOffice": "彦根地方気象台",
    "reportDatetime": "2026-04-22T17:00:00+09:00",
    "timeSeries": [
      {
        "timeDefines": [
          "2026-04-23T00:00:00+09:00",
          "2026-04-24T00:00:00+09:00",
          "2026-04-25T00:00:00+09:00",
          "2026-04-26T00:00:00+09:00",
          "2026-04-27T00:00:00+09:00",
          "2026-04-28T00:00:00+09:00",
          "2026-04-29T00:00:00+09:00"
        ],
        "areas": [
          {
            "area": {
              "name": "滋賀県",
              "code": "250000"
            },
            "weatherCodes": [
              "302",
              "211",
              "101",
              "201",
              "201",
              "200",
              "200"
            ],
            "pops": [
              "",
              "20",
              "20",
              "30",
              "30",
              "30",
              "40"
            ],
            "reliabilities": [
              "",
              "",
              "A",
              "A",
              "C",
              "B",
              "C"
            ]
          }
        ]
      },
      {
        "timeDefines": [
          "2026-04-23T00:00:00+09:00",
          "2026-04-24T00:00:00+09:00",
          "2026-04-25T00:00:00+09:00",
          "2026-04-26T00:00:00+09:00",
          "2026-04-27T00:00:00+09:00",
          "2026-04-28T00:00:00+09:00",
          "2026-04-29T00:00:00+09:00"
        ],
        "areas": [
          {
            "area": {
              "name": "彦根",
              "code": "60131"
            },
            "tempsMin": [
              "",
              "11",
              "10",
              "11",
              "11",
              "12",
              "13"
            ],
            "tempsMinUpper": [
              "",
              "12",
              "12",
              "13",
              "13",
              "14",
              "15"
            ],
            "tempsMinLower": [
              "",
              "9",
              "7",
              "9",
              "9",
              "9",
              "10"
            ],
            "tempsMax": [
              "",
              "18",
              "19",
              "20",
              "21",
              "23",
              "22"
            ],
            "tempsMaxUpper": [
              "",
              "21",
              "21",
              "21",
              "23",
              "25",
              "24"
            ],
            "tempsMaxLower": [
              "",
              "17",
              "17",
              "18",
              "19",
              "20",
              "19"
            ]
          }
        ]
      }
    ],
    "tempAverage": {
      "areas": [
        {
          "area": {
            "name": "彦根",
            "code": "60131"
          },
          "min": "10.1",
          "max": "19.6"
        }
      ]
    },
    "precipAverage": {
      "areas": [
        {
          "area": {
            "name": "彦根",
            "code": "60131"
          },
          "min": "13.3",
          "max": "31.8"
        }
      ]
    }
  }
]